asyncworker/__init__.py
asyncworker/app.py
asyncworker/bucket.py
asyncworker/conf.py
asyncworker/connections.py
asyncworker/consumer.py
asyncworker/exceptions.py
asyncworker/options.py
asyncworker/routes.py
asyncworker/task_runners.py
asyncworker/time.py
asyncworker/utils.py
asyncworker/easyqueue/__init__.py
asyncworker/easyqueue/connection.py
asyncworker/easyqueue/exceptions.py
asyncworker/easyqueue/message.py
asyncworker/easyqueue/queue.py
asyncworker/http/__init__.py
asyncworker/http/decorators.py
asyncworker/http/wrapper.py
asyncworker/metrics/__init__.py
asyncworker/metrics/aiohttp_resources.py
asyncworker/metrics/buckets.py
asyncworker/metrics/registry.py
asyncworker/metrics/types.py
asyncworker/metrics/collectors/__init__.py
asyncworker/metrics/collectors/base.py
asyncworker/metrics/collectors/gc.py
asyncworker/metrics/collectors/platform.py
asyncworker/metrics/collectors/process.py
asyncworker/metrics/definitions/__init__.py
asyncworker/metrics/definitions/amqp.py
asyncworker/metrics/definitions/http.py
asyncworker/rabbitmq/__init__.py
asyncworker/rabbitmq/message.py
asyncworker/signals/__init__.py
asyncworker/signals/base.py
asyncworker/signals/handlers/__init__.py
asyncworker/signals/handlers/base.py
asyncworker/signals/handlers/http.py
asyncworker/signals/handlers/rabbitmq.py
asyncworker/signals/handlers/sse.py
asyncworker/sse/__init__.py
asyncworker/sse/consumer.py
asyncworker/sse/message.py
asyncworker/testing/__init__.py
asyncworker/types/__init__.py
asyncworker/types/registry.py
asyncworker/types/resolver.py
async_worker-0.15.1.dist-info/LICENSE
async_worker-0.15.1.dist-info/METADATA
async_worker-0.15.1.dist-info/WHEEL
async_worker-0.15.1.dist-info/top_level.txt
async_worker-0.15.1.dist-info/RECORD
