Metadata-Version: 2.1
Name: async-worker
Version: 0.15.1
Summary: Microframework para escrever workers assíncronos em Python
Home-page: https://github.com/b2wdigital/async-worker
Author: Dalton Barreto
Author-email: daltonmatos@gmail.com
License: MIT
Platform: UNKNOWN
Classifier: Programming Language :: Python :: 3.6
Classifier: Programming Language :: Python :: 3.7
Classifier: Programming Language :: Python :: 3.8
Requires-Dist: aioamqp (==0.14.0)
Requires-Dist: aiologger (==0.5.0)
Requires-Dist: pydantic (<2.0,>=0.32.2)
Requires-Dist: cached-property (==1.5.1)
Requires-Dist: aiohttp (==3.6.2)
Requires-Dist: prometheus-client (==0.7.1)
